sri_xades_signer/__init__.py
sri_xades_signer/signer.py
sri_xades_signer-1.0.0.dist-info/licenses/LICENSE
sri_xades_signer-1.0.0.dist-info/METADATA
sri_xades_signer-1.0.0.dist-info/WHEEL
sri_xades_signer-1.0.0.dist-info/top_level.txt
sri_xades_signer-1.0.0.dist-info/RECORD
