Metadata-Version: 2.4
Name: sri-xades-signer
Version: 1.0.0
Summary: A Python library to generate XML digital signatures (XAdES-BES) compliant with Ecuador's SRI electronic invoicing requirements.
Author: Juan Malo
License: GNU AFFERO GENERAL PUBLIC LICENSE
Project-URL: Homepage, https://github.com/Juanja1306/SRI-Xades-Signer
Project-URL: Documentation, https://github.com/Juanja1306/SRI-Xades-Signer#readme
Project-URL: Issues, https://github.com/Juanja1306/SRI-Xades-Signer/issues
Requires-Python: >=3.10
License-File: LICENSE
Requires-Dist: cryptography>=45.0.6
Requires-Dist: lxml>=5.4.0
Dynamic: license-file
